[
  {
    "name": "Михаил Хазин",
    "expertise_level": "академический_учёный",
    "topic_area": "экономика",
    "claims": [
      {
        "claim_id": 1,
        "text": "Трамп, Путин и Си хотят войти в кризис без большой войны.",
        "topic": "геополитика",
        "is_forecast": true,
        "confidence": null
      },
      {
        "claim_id": 2,
        "text": "Англичане раскачивают Армению, потому что это самая близкая точка, которую они могут раскачать.",
        "topic": "геополитика",
        "is_forecast": false,
        "confidence": null
      },
      {
        "claim_id": 3,
        "text": "Трамп взял контроль над ФРС через Кевина Варшавского.",
        "topic": "экономика",
        "is_forecast": false,
        "confidence": null
      },
      {
        "claim_id": 4,
        "text": "Старая капитализация рухнет, пойдёт новая, создавать её будет ФРС, а распределять администрация.",
        "topic": "экономика",
        "is_forecast": true,
        "confidence": null
      },
      {
        "claim_id": 5,
        "text": "Доходность в финансовом секторе выше, чем в реальном, поэтому из финансового сектора никто деньги не вкладывает в реальность.",
        "topic": "экономика",
        "is_forecast": false,
        "confidence": null
      },
      {
        "claim_id": 6,
        "text": "В США реальный сектор падает, а богатые люди выводят деньги из финансов, вызывая инфляцию в реальном секторе.",
        "topic": "экономика",
        "is_forecast": false,
        "confidence": null
      },
      {
        "claim_id": 7,
        "text": "Инфляция в США в апреле 10% в годовом выражении, что почти 1% в месяц — это катастрофа, как перед Великой депрессией.",
        "topic": "экономика",
        "is_forecast": false,
        "confidence": null
      },
      {
        "claim_id": 8,
        "text": "Уверенность потребителей в США в марте, апреле и мае 2024 года показывала абсолютные минимумы за всю историю наблюдений.",
        "topic": "экономика",
        "is_forecast": false,
        "confidence": null
      },
      {
        "claim_id": 9,
        "text": "Начнётся обвал финансовых пузырей, и Кевин Варшавский будет минимизировать спад.",
        "topic": "экономика",
        "is_forecast": true,
        "confidence": null
      },
      {
        "claim_id": 10,
        "text": "Механизм кризиса: падение фондовых рынков снижает стоимость залоговых активов, банки требуют переоценки, кредитование сжимается, экономика падает.",
        "topic": "экономика",
        "is_forecast": false,
        "confidence": null
      },
      {
        "claim_id": 11,
        "text": "Сейчас доля финансового сектора относительно реального составляет около 50%, а историческая норма — 5%. При кризисе сгорит более 10 триллионов долларов активов.",
        "topic": "экономика",
        "is_forecast": true,
        "confidence": null
      },
      {
        "claim_id": 12,
        "text": "Государство будет финансировать экономику из бюджета, а ФРС печатать деньги для новых компаний — повторение схемы Рузвельта.",
        "topic": "экономика",
        "is_forecast": true,
        "confidence": null
      },
      {
        "claim_id": 13,
        "text": "Связка Орш-Трамп делается под схему Рузвельта: Трамп уйдёт через 2 года, но кризис начнётся, и архитектура закладывается сейчас.",
        "topic": "экономика",
        "is_forecast": true,
        "confidence": null
      },
      {
        "claim_id": 14,
        "text": "Вся капитализация, построенная на нынешней модели, обратится в ноль.",
        "topic": "экономика",
        "is_forecast": true,
        "confidence": null
      },
      {
        "claim_id": 15,
        "text": "Падение уровня жизни населения в США будет около 40%, что неминуемо ведёт либо к распаду страны, либо к тотальной диктатуре.",
        "topic": "экономика",
        "is_forecast": true,
        "confidence": null
      },
      {
        "claim_id": 16,
        "text": "В Европе после кризиса практически не останется демократических стран, как в 1930-е годы.",
        "topic": "геополитика",
        "is_forecast": true,
        "confidence": null
      },
      {
        "claim_id": 17,
        "text": "Диктатуры в крупных странах сегодня быть не может, потому что нет среды для диктатора — управляют наёмные менеджеры под контролем банкиров.",
        "topic": "геополитика",
        "is_forecast": false,
        "confidence": null
      },
      {
        "claim_id": 18,
        "text": "Когда финансовая система рухнет, банкиры потеряют контроль, политики типа Урсулы фон дер Ляйен или Макрона не поймут, что происходит, и либо их снесут, либо они убегут.",
        "topic": "геополитика",
        "is_forecast": true,
        "confidence": null
      },
      {
        "claim_id": 19,
        "text": "Банкиры боятся бонапартизма и не пустят к власти реального генерала или бандита, поэтому мир свалится в экономику полевых командиров.",
        "topic": "геополитика",
        "is_forecast": true,
        "confidence": null
      },
      {
        "claim_id": 20,
        "text": "Россия может не свалиться в экономику полевых командиров, а Западная Европа, Центральная Азия, Ближний Восток, Африка, Латинская Америка и США — почти наверняка.",
        "topic": "геополитика",
        "is_forecast": true,
        "confidence": null
      },
      {
        "claim_id": 21,
        "text": "В США образуется линия фронтира с запада на восток, где правят наркокартели и полевые командиры, и реднеки легче договорятся с ними, чем с либералами.",
        "topic": "геополитика",
        "is_forecast": true,
        "confidence": null
      },
      {
        "claim_id": 22,
        "text": "Главный враг Трампа — не Путин и не Си, а Лондон, а также остатки либералов в США (Калифорния, Нью-Йорк) и евроатлантические элиты.",
        "topic": "геополитика",
        "is_forecast": false,
        "confidence": null
      },
      {
        "claim_id": 23,
        "text": "Для Брюсселя и Лондона принципиально важно начать войну с Россией до осени, даже если это идиотический сценарий, лишь бы сохранить власть.",
        "topic": "геополитика",
        "is_forecast": true,
        "confidence": null
      },
      {
        "claim_id": 24,
        "text": "Путин пригрозил Макрону потопить авианосец «Шарль де Голль» в Балтийском море, после чего авианосец увели в Средиземное море.",
        "topic": "геополитика",
        "is_forecast": false,
        "confidence": null
      },
      {
        "claim_id": 25,
        "text": "Сейчас есть силы, которые не хотят войны, в отличие от 1939 года, и нет военной промышленности — не хватает смежников для производства ракет.",
        "topic": "геополитика",
        "is_forecast": false,
        "confidence": null
      },
      {
        "claim_id": 26,
        "text": "Индия вышла из большой политики, потому что брахманы решили не воевать с Китаем или Пакистаном, а ключевым становится коридор Север-Юг.",
        "topic": "геополитика",
        "is_forecast": false,
        "confidence": null
      },
      {
        "claim_id": 27,
        "text": "Англичане раскачивают Армению, потому что это самая близкая точка для дестабилизации, а в Азербайджане у них проблемы.",
        "topic": "геополитика",
        "is_forecast": false,
        "confidence": null
      },
      {
        "claim_id": 28,
        "text": "Люди, думающие о будущем, вкладываются в коридор Север-Юг, потому что там будут деньги через 5 лет.",
        "topic": "экономика",
        "is_forecast": true,
        "confidence": null
      },
      {
        "claim_id": 29,
        "text": "Мир возвращается в парадигму автаркии и диктатуры, где ключевыми факторами будут личная ответственность, смена экономической парадигмы и понимание экономической механики.",
        "topic": "экономика",
        "is_forecast": true,
        "confidence": null
      }
    ]
  }
]